GaojiBashJiaobenBianchengZhinan391YangchunminHuangyiYi/README.md
GaojiBashJiaobenBianchengZhinan391YangchunminHuangyiYi/__init__.py
GaojiBashJiaobenBianchengZhinan391YangchunminHuangyiYi/__main__.py
GaojiBashJiaobenBianchengZhinan391YangchunminHuangyiYi/file.pdf
GaojiBashJiaobenBianchengZhinan391YangchunminHuangyiYi/index.html
gaoji_bash_jiaoben_biancheng_zhinan_3_9_1_yangchunmin_huangyi_yi-2024.3.2.0.dist-info/METADATA
gaoji_bash_jiaoben_biancheng_zhinan_3_9_1_yangchunmin_huangyi_yi-2024.3.2.0.dist-info/WHEEL
gaoji_bash_jiaoben_biancheng_zhinan_3_9_1_yangchunmin_huangyi_yi-2024.3.2.0.dist-info/entry_points.txt
gaoji_bash_jiaoben_biancheng_zhinan_3_9_1_yangchunmin_huangyi_yi-2024.3.2.0.dist-info/top_level.txt
gaoji_bash_jiaoben_biancheng_zhinan_3_9_1_yangchunmin_huangyi_yi-2024.3.2.0.dist-info/RECORD
