Metadata-Version: 2.1
Name: gaoji-bash-jiaoben-biancheng-zhinan-3-9-1-yangchunmin-huangyi-yi
Version: 2024.3.2.0
Summary: 高级Bash脚本编程指南 3.9.1 (杨春敏 黄毅 译)
Home-page: https://github.com/apachecn/gaoji-bash-jiaoben-biancheng-zhinan-3-9-1-yangchunmin-huangyi-yi
Author: ApacheCN
Author-email: apachecn@163.com
License: UNKNOWN
Platform: UNKNOWN
Classifier: Development Status :: 4 - Beta
Classifier: Environment :: Console
Classifier: Intended Audience :: Developers
Classifier: Intended Audience :: End Users/Desktop
Classifier: License :: Other/Proprietary License
Classifier: Natural Language :: Chinese (Simplified)
Classifier: Natural Language :: English
Classifier: Operating System :: OS Independent
Classifier: Programming Language :: Python :: 3
Classifier: Programming Language :: Python :: 3 :: Only
Classifier: Programming Language :: Python :: 3.6
Classifier: Programming Language :: Python :: 3.7
Classifier: Topic :: Text Processing :: Markup :: Markdown
Classifier: Topic :: Text Processing :: Markup :: HTML
Classifier: Topic :: Internet :: WWW/HTTP
Classifier: Topic :: Software Development :: Documentation
Classifier: Topic :: Documentation
Requires-Python: >=3.6
